json_schema_to_pydantic/__init__.py
json_schema_to_pydantic/builders.py
json_schema_to_pydantic/exceptions.py
json_schema_to_pydantic/handlers.py
json_schema_to_pydantic/interfaces.py
json_schema_to_pydantic/model_builder.py
json_schema_to_pydantic/models.py
json_schema_to_pydantic/resolvers.py
json_schema_to_pydantic-0.4.8.dist-info/METADATA
json_schema_to_pydantic-0.4.8.dist-info/WHEEL
json_schema_to_pydantic-0.4.8.dist-info/licenses/LICENSE
json_schema_to_pydantic-0.4.8.dist-info/RECORD
