Metadata-Version: 2.4
Name: json-schema-to-pydantic
Version: 0.4.8
Summary: A Python library for automatically generating Pydantic v2 models from JSON Schema definitions
Project-URL: Homepage, https://github.com/richard-gyiko/json-schema-to-pydantic
Project-URL: Bug-Tracker, https://github.com/richard-gyiko/json-schema-to-pydantic/issues
Project-URL: Documentation, https://github.com/richard-gyiko/json-schema-to-pydantic#readme
Author-email: Richard Gyiko <gyiko.richard@outlook.com>
License-Expression: MIT
License-File: LICENSE
Keywords: conversion,json-schema,pydantic,schema,validation
Classifier: Development Status :: 4 - Beta
Classifier: Intended Audience :: Developers
Classifier: License :: OSI Approved :: MIT License
Classifier: Programming Language :: Python :: 3
Classifier: Programming Language :: Python :: 3.10
Classifier: Programming Language :: Python :: 3.11
Classifier: Programming Language :: Python :: 3.12
Classifier: Topic :: Software Development :: Libraries :: Python Modules
Classifier: Typing :: Typed
Requires-Python: >=3.9
Requires-Dist: pydantic>=2.10.4
Provides-Extra: dev
Requires-Dist: pytest-cov>=6.0.0; extra == 'dev'
Requires-Dist: pytest>=8.3.4; extra == 'dev'
